setup.py
thumbor_no_result/__init__.py
thumbor_no_result.egg-info/PKG-INFO
thumbor_no_result.egg-info/SOURCES.txt
thumbor_no_result.egg-info/dependency_links.txt
thumbor_no_result.egg-info/top_level.txt
thumbor_no_result/result_storages/__init__.py
thumbor_no_result/result_storages/noop_storage.py