Metadata-Version: 1.1
Name: thumbor-no-result
Version: 0.1
Summary: No Result Storage adapter addon for Thumbor
Home-page: https://github.com/CodingNinja/thumbor_no_result
Author: David Mann
Author-email: ninja@codingninja.com.au
License: MIT
Keywords: thumbor,images,cloud,cdn
Platform: UNKNOWN
Classifier: Development Status :: 4 - Beta
Classifier: Intended Audience :: Developers
Classifier: License :: OSI Approved :: MIT License
Classifier: Natural Language :: English
Classifier: Operating System :: POSIX :: Linux
Classifier: Programming Language :: Python :: 2.6
Classifier: Topic :: Internet :: WWW/HTTP :: Dynamic Content
Classifier: Topic :: Multimedia :: Graphics :: Presentation
Requires: thumbor
Requires: pyrax
